{
    "code": "01028060",
    "url": "https:\/\/service.mohw.gov.tw\/DOCMAP\/CusSite\/TCMLResultDetail.aspx?LICEWORDID=01&LICENUM=028060",
    "中文品名": "“南和”七厘操力散",
    "英文品名": "",
    "許可證字號": "衛署藥製字第028060號",
    "發證日期": "1993-11-24",
    "有效日期": "2005-02-28",
    "製造商名稱": "臺灣三陽製藥廠股份有限公司",
    "製造商地址": "屏東縣潮州鎮蓬萊里榮田路３６號",
    "申請商名稱": "上禾興藥業有限公司",
    "效能": "",
    "適應症": "打撲傷引起之胸部疼痛、祛傷解鬱",
    "劑型": "散劑",
    "類別": "須由中醫師處方使用",
    "包裝": "24~500、600、1000公克",
    "單複方": "複方",
    "限制項目": "",
    "ingredients": [
        {
            "成分名稱": "",
            "含量描述": "每一公克中含有：",
            "含量": "",
            "單位": ""
        },
        {
            "成分名稱": "紅花",
            "含量描述": "",
            "含量": "117.0000",
            "單位": "mg"
        },
        {
            "成分名稱": "百合",
            "含量描述": "",
            "含量": "117.0000",
            "單位": "mg"
        },
        {
            "成分名稱": "當歸",
            "含量描述": "",
            "含量": "107.0000",
            "單位": "mg"
        },
        {
            "成分名稱": "乳香",
            "含量描述": "",
            "含量": "117.0000",
            "單位": "mg"
        },
        {
            "成分名稱": "木香",
            "含量描述": "",
            "含量": "117.0000",
            "單位": "mg"
        },
        {
            "成分名稱": "硃砂",
            "含量描述": "",
            "含量": "5.0000",
            "單位": "mg"
        },
        {
            "成分名稱": "血竭",
            "含量描述": "",
            "含量": "110.0000",
            "單位": "mg"
        },
        {
            "成分名稱": "玄參",
            "含量描述": "",
            "含量": "100.0000",
            "單位": "mg"
        },
        {
            "成分名稱": "梅片",
            "含量描述": "",
            "含量": "10.0000",
            "單位": "mg"
        },
        {
            "成分名稱": "沒藥",
            "含量描述": "",
            "含量": "100.0000",
            "單位": "mg"
        },
        {
            "成分名稱": "桔梗",
            "含量描述": "",
            "含量": "100.0000",
            "單位": "mg"
        }
    ]
}