{
    "code": "01035315",
    "url": "https:\/\/service.mohw.gov.tw\/DOCMAP\/CusSite\/TCMLResultDetail.aspx?LICEWORDID=01&LICENUM=035315",
    "中文品名": "“正揚” 懷牛膝濃縮散",
    "英文品名": "HWAI NIOU SHI Extract Powder \"C.Y.\"",
    "許可證字號": "衛署藥製字第035315號",
    "發證日期": "2017-03-28",
    "有效日期": "2022-06-01",
    "製造商名稱": "國科生技製藥股份有限公司",
    "製造商地址": "桃園縣龍潭鄉三水里大北坑街一段２２０巷６５號",
    "申請商名稱": null,
    "效能": "破血、通經、強腰膝、利水。",
    "適應症": "",
    "劑型": "濃縮散劑",
    "類別": "調劑專用",
    "包裝": "2.4~1000公克塑膠瓶裝",
    "單複方": "單方",
    "限制項目": "",
    "ingredients": [
        {
            "成分名稱": "",
            "含量描述": "每1.2公克中含有： ",
            "含量": "",
            "單位": ""
        },
        {
            "成分名稱": "牛膝",
            "含量描述": "",
            "含量": "4.0",
            "單位": "g"
        },
        {
            "成分名稱": "",
            "含量描述": "以上生藥製成浸膏0.8g",
            "含量": "",
            "單位": ""
        },
        {
            "成分名稱": "澱粉",
            "含量描述": "",
            "含量": "0.4",
            "單位": "g"
        }
    ]
}