{
    "code": "01036800",
    "url": "https:\/\/service.mohw.gov.tw\/DOCMAP\/CusSite\/TCMLResultDetail.aspx?LICEWORDID=01&LICENUM=036800",
    "中文品名": "“勝昌”血府逐瘀湯濃縮散",
    "英文品名": "Xue Fu Zhu Yu Tang Extract Powder \"Sheng Chang\"",
    "許可證字號": "衛署藥製字第036800號",
    "發證日期": "2018-05-23",
    "有效日期": "2023-10-06",
    "製造商名稱": "勝昌製藥廠股份有限公司中壢廠",
    "製造商地址": "桃園市中壢區民族路六段４３６、４３６之１號",
    "申請商名稱": "勝昌製藥廠股份有限公司中壢廠",
    "效能": "活血化瘀、行氣止痛。",
    "適應症": "胸中血瘀、日晡潮熱、經年胸痛、頭痛、或呃逆不止、或內熱煩悶、心悸失眠。",
    "劑型": "濃縮散劑",
    "類別": "須由中醫師處方使用",
    "包裝": "30~1000公克鋁箔袋盒裝及塑膠瓶裝",
    "單複方": "複方",
    "限制項目": "",
    "ingredients": [
        {
            "成分名稱": "",
            "含量描述": "每15公克中含有：",
            "含量": "",
            "單位": ""
        },
        {
            "成分名稱": "當歸",
            "含量描述": "",
            "含量": "4.5",
            "單位": "g"
        },
        {
            "成分名稱": "生地黃",
            "含量描述": "",
            "含量": "4.5",
            "單位": "g"
        },
        {
            "成分名稱": "桃仁",
            "含量描述": "",
            "含量": "6.0",
            "單位": "g"
        },
        {
            "成分名稱": "紅花",
            "含量描述": "",
            "含量": "4.5",
            "單位": "g"
        },
        {
            "成分名稱": "枳殼",
            "含量描述": "",
            "含量": "3.0",
            "單位": "g"
        },
        {
            "成分名稱": "赤芍",
            "含量描述": "",
            "含量": "3.0",
            "單位": "g"
        },
        {
            "成分名稱": "柴胡",
            "含量描述": "",
            "含量": "1.5",
            "單位": "g"
        },
        {
            "成分名稱": "甘草",
            "含量描述": "",
            "含量": "1.5",
            "單位": "g"
        },
        {
            "成分名稱": "桔梗",
            "含量描述": "",
            "含量": "2.3",
            "單位": "g"
        },
        {
            "成分名稱": "川芎",
            "含量描述": "",
            "含量": "2.3",
            "單位": "g"
        },
        {
            "成分名稱": "川牛膝",
            "含量描述": "",
            "含量": "4.5",
            "單位": "g"
        },
        {
            "成分名稱": "以上生藥製成浸膏9.6g",
            "含量描述": "",
            "含量": "37.6:9.6=3.9:1",
            "單位": ""
        },
        {
            "成分名稱": "澱粉",
            "含量描述": "",
            "含量": "5.4",
            "單位": "g"
        }
    ]
}