{
    "code": "01042012",
    "url": "https:\/\/service.mohw.gov.tw\/DOCMAP\/CusSite\/TCMLResultDetail.aspx?LICEWORDID=01&LICENUM=042012",
    "中文品名": "”富田”炙甘草湯濃縮錠",
    "英文品名": "ZHI GAN CAO TANG CONC TAB \"F.T.\"",
    "許可證字號": "衛署藥製字第042012號",
    "發證日期": "1998-03-27",
    "有效日期": "2023-03-27",
    "製造商名稱": "富田製藥廠股份有限公司",
    "製造商地址": "彰化縣伸港鄉溪底村興工路四三號",
    "申請商名稱": null,
    "效能": "益氣補血、滋陰復脈。",
    "適應症": "氣虛血少脈結代、心動悸、氣短胸悶、虛勞肺痿。",
    "劑型": "濃縮錠劑",
    "類別": "須由中醫師處方使用",
    "包裝": "120~1000錠  塑膠瓶裝",
    "單複方": "複方",
    "限制項目": "",
    "ingredients": [
        {
            "成分名稱": "",
            "含量描述": "每錠（340mg）中含有：",
            "含量": "",
            "單位": ""
        },
        {
            "成分名稱": "炙甘草",
            "含量描述": "",
            "含量": "48.4",
            "單位": "mg"
        },
        {
            "成分名稱": "生薑",
            "含量描述": "",
            "含量": "40.3",
            "單位": "mg"
        },
        {
            "成分名稱": "桂枝",
            "含量描述": "",
            "含量": "40.3",
            "單位": "mg"
        },
        {
            "成分名稱": "人參",
            "含量描述": "",
            "含量": "24.2",
            "單位": "mg"
        },
        {
            "成分名稱": "生地黃",
            "含量描述": "",
            "含量": "193.4",
            "單位": "mg"
        },
        {
            "成分名稱": "阿膠",
            "含量描述": "",
            "含量": "24.2",
            "單位": "mg"
        },
        {
            "成分名稱": "麥門冬",
            "含量描述": "",
            "含量": "40.3",
            "單位": "mg"
        },
        {
            "成分名稱": "火麻仁",
            "含量描述": "",
            "含量": "48.4",
            "單位": "mg"
        },
        {
            "成分名稱": "大棗",
            "含量描述": "",
            "含量": "48.4",
            "單位": "mg"
        },
        {
            "成分名稱": "",
            "含量描述": "以上生藥製成浸膏比例162.71mg（生藥與浸膏比例507.9：162.71＝3.12：1）",
            "含量": "",
            "單位": ""
        },
        {
            "成分名稱": "澱粉",
            "含量描述": "",
            "含量": "161.18",
            "單位": "mg"
        },
        {
            "成分名稱": "滑石粉",
            "含量描述": "",
            "含量": "16.11",
            "單位": "mg"
        }
    ]
}