{
    "code": "01043885",
    "url": "https:\/\/service.mohw.gov.tw\/DOCMAP\/CusSite\/TCMLResultDetail.aspx?LICEWORDID=01&LICENUM=043885",
    "time": "2020-03-05 01:51:47",
    "中文品名": "“生春”生脈飲濃縮細粒",
    "英文品名": "Sheng Mo Yin Concentrated Fine Granule \"Sheng Chun\"",
    "許可證字號": "衛署藥製字第043885號",
    "發證日期": "2000-07-21",
    "有效日期": "2025-07-21",
    "製造商名稱": "立康生物科技股份有限公司工廠",
    "製造商地址": "臺南市永康區環工路29、31、31之1、31之2、31之3、31之5號",
    "申請商名稱": "生春堂製藥工業股份有限公司",
    "效能": "",
    "適應症": "熱傷元氣、氣短倦怠、口渴多汗。",
    "劑型": "濃縮顆粒劑",
    "類別": "須由中醫師處方使用",
    "包裝": "30~1000公克塑膠瓶裝",
    "單複方": "複方",
    "限制項目": "",
    "ingredients": [
        {
            "成分名稱": "",
            "含量描述": "每17公克中含有:",
            "含量": "",
            "單位": ""
        },
        {
            "成分名稱": "人參",
            "含量描述": "",
            "含量": "10",
            "單位": "g"
        },
        {
            "成分名稱": "麥門冬",
            "含量描述": "",
            "含量": "6",
            "單位": "g"
        },
        {
            "成分名稱": "五味子",
            "含量描述": "",
            "含量": "4",
            "單位": "g"
        },
        {
            "成分名稱": "",
            "含量描述": "以上生藥製成浸膏8.5g",
            "含量": "",
            "單位": ""
        },
        {
            "成分名稱": "澱粉",
            "含量描述": "",
            "含量": "8.5",
            "單位": "g"
        }
    ]
}