{
    "code": "01046304",
    "url": "https:\/\/service.mohw.gov.tw\/DOCMAP\/CusSite\/TCMLResultDetail.aspx?LICEWORDID=01&LICENUM=046304",
    "中文品名": "“三帆”當歸芍藥散濃縮細粒",
    "英文品名": "Dang Guei Shaur Yaw Saan Concentrated Granule“S.F.”",
    "許可證字號": "衛署藥製字第046304號",
    "發證日期": "2004-06-04",
    "有效日期": "2029-06-04",
    "製造商名稱": "臺灣三帆製藥科技股份有限公司",
    "製造商地址": "臺南市永康區王行里經中路3號",
    "申請商名稱": "臺灣三帆製藥科技股份有限公司",
    "效能": "補血養肝、健脾滲濕。",
    "適應症": "月經不調、妊娠腰疼痛、頭暈、腰腳冷感。",
    "劑型": "濃縮顆粒劑",
    "類別": "須由中醫師處方使用",
    "包裝": "18~1000公克塑膠瓶及3公克鋁箔包×6~333包盒裝",
    "單複方": "複方",
    "限制項目": "",
    "ingredients": [
        {
            "成分名稱": "",
            "含量描述": "每9.0公克中含有：",
            "含量": "",
            "單位": ""
        },
        {
            "成分名稱": "當歸",
            "含量描述": "",
            "含量": "2.0",
            "單位": "g"
        },
        {
            "成分名稱": "白芍",
            "含量描述": "",
            "含量": "10.0",
            "單位": "g"
        },
        {
            "成分名稱": "茯苓",
            "含量描述": "",
            "含量": "2.5",
            "單位": "g"
        },
        {
            "成分名稱": "白朮",
            "含量描述": "",
            "含量": "2.5",
            "單位": "g"
        },
        {
            "成分名稱": "澤瀉",
            "含量描述": "",
            "含量": "5.0",
            "單位": "g"
        },
        {
            "成分名稱": "川芎",
            "含量描述": "",
            "含量": "5.0",
            "單位": "g"
        },
        {
            "成分名稱": "",
            "含量描述": "以上生藥製成浸膏4.5g",
            "含量": "",
            "單位": ""
        },
        {
            "成分名稱": "澱粉",
            "含量描述": "",
            "含量": "4.5",
            "單位": "g"
        }
    ]
}