{
    "code": "01047529",
    "url": "https:\/\/service.mohw.gov.tw\/DOCMAP\/CusSite\/TCMLResultDetail.aspx?LICEWORDID=01&LICENUM=047529",
    "time": "2020-03-05 01:51:47",
    "中文品名": "“仙豐”抵當湯濃縮細粒",
    "英文品名": "DII DANG TANG EXTRACT S.G“SHENG FOONG”",
    "許可證字號": "衛署藥製字第047529號",
    "發證日期": "2005-09-06",
    "有效日期": "2020-09-06",
    "製造商名稱": "仙豐股份有限公司蘇澳製藥廠",
    "製造商地址": "宜蘭縣蘇澳鎮大圳路６３巷２５號",
    "申請商名稱": "仙豐股份有限公司蘇澳製藥廠",
    "效能": "攻逐瘀血。",
    "適應症": "下焦蓄血、少腹硬滿、經水不利。",
    "劑型": "濃縮顆粒劑",
    "類別": "須由中醫師處方使用",
    "包裝": "18-1000公克塑膠瓶裝",
    "單複方": "複方",
    "限制項目": "",
    "ingredients": [
        {
            "成分名稱": "",
            "含量描述": "每9公克中含有：",
            "含量": "",
            "單位": ""
        },
        {
            "成分名稱": "水蛭",
            "含量描述": "",
            "含量": "10",
            "單位": "g"
        },
        {
            "成分名稱": "蟲",
            "含量描述": "",
            "含量": "1",
            "單位": "g"
        },
        {
            "成分名稱": "桃仁",
            "含量描述": "",
            "含量": "2",
            "單位": "g"
        },
        {
            "成分名稱": "酒大黃",
            "含量描述": "",
            "含量": "10",
            "單位": "g"
        },
        {
            "成分名稱": "",
            "含量描述": "以上生藥製成浸膏4.5g（生藥與浸膏比例23:4.5=5.1:1）",
            "含量": "",
            "單位": ""
        },
        {
            "成分名稱": "澱粉",
            "含量描述": "",
            "含量": "4.5",
            "單位": "g"
        }
    ]
}