{
    "code": "01050603",
    "url": "https:\/\/service.mohw.gov.tw\/DOCMAP\/CusSite\/TCMLResultDetail.aspx?LICEWORDID=01&LICENUM=050603",
    "中文品名": "“華陀”人參散 （單味）",
    "英文品名": "“Hua To” Ren Shen Powder",
    "許可證字號": "衛署藥製字第050603號",
    "發證日期": "2009-08-20",
    "有效日期": "2024-08-20",
    "製造商名稱": "北京同仁堂生物科技股份有限公司高雄廠",
    "製造商地址": "高雄市彌陀區產業路156號",
    "申請商名稱": null,
    "效能": "補脾、益氣、強壯、生津",
    "適應症": "",
    "劑型": "散劑",
    "類別": "調劑或調配專用",
    "包裝": "1~1000g鋁箔袋、塑膠袋及塑膠瓶裝",
    "單複方": "單方",
    "限制項目": "",
    "ingredients": [
        {
            "成分名稱": "",
            "含量描述": "人參",
            "含量": "",
            "單位": ""
        }
    ]
}