{
    "code": "01053416",
    "url": "https:\/\/service.mohw.gov.tw\/DOCMAP\/CusSite\/TCMLResultDetail.aspx?LICEWORDID=01&LICENUM=053416",
    "中文品名": "\"裕元堂\"杜仲散",
    "英文品名": "\"Yuh Yuan Tarng\" Duh Jonq Powder",
    "許可證字號": "衛署藥製字第053416號",
    "發證日期": "2010-04-15",
    "有效日期": "2015-04-15",
    "製造商名稱": "北京同仁堂生物科技股份有限公司高雄廠",
    "製造商地址": "高雄市彌陀區產業路156號",
    "申請商名稱": "裕元堂生藥科技有限公司",
    "效能": "強筋骨",
    "適應症": "",
    "劑型": "散劑",
    "類別": "調劑或調配專用",
    "包裝": "1000公克以下鋁箔袋、塑膠袋及塑膠瓶裝",
    "單複方": "單方",
    "限制項目": "",
    "ingredients": [
        {
            "成分名稱": "",
            "含量描述": "杜仲",
            "含量": "",
            "單位": ""
        }
    ]
}