{
    "code": "01058480",
    "url": "https:\/\/service.mohw.gov.tw\/DOCMAP\/CusSite\/TCMLResultDetail.aspx?LICEWORDID=01&LICENUM=058480",
    "中文品名": "“三才堂”加味逍遙散濃縮細粒",
    "英文品名": "“S.T.T”JIA WEI XIAO YAO SAN EXTRACT SUBTLY GRANULE",
    "許可證字號": "衛部藥製字第058480號",
    "發證日期": "2015-03-14",
    "有效日期": "2030-03-14",
    "製造商名稱": "三才堂製藥廠有限公司",
    "製造商地址": "桃園市楊梅區梅溪里新農街二段２０９巷６１弄９號",
    "申請商名稱": "三才堂製藥廠有限公司",
    "效能": "疏肝解鬱、清熱涼血",
    "適應症": "肝鬱血虛發熱、月經不調、怔忡不寧",
    "劑型": "濃縮顆粒劑",
    "類別": "須由中醫師處方使用",
    "包裝": "33~1000公克塑膠罐裝及鋁箔袋裝4.1公克鋁箔袋x8~243袋盒裝",
    "單複方": "複方",
    "限制項目": "",
    "ingredients": [
        {
            "成分名稱": "",
            "含量描述": "每16.5公克中含有：",
            "含量": "",
            "單位": ""
        },
        {
            "成分名稱": "當歸",
            "含量描述": "",
            "含量": "4",
            "單位": "g"
        },
        {
            "成分名稱": "白朮",
            "含量描述": "",
            "含量": "4",
            "單位": "g"
        },
        {
            "成分名稱": "白芍",
            "含量描述": "",
            "含量": "4",
            "單位": "g"
        },
        {
            "成分名稱": "柴胡",
            "含量描述": "",
            "含量": "4",
            "單位": "g"
        },
        {
            "成分名稱": "茯苓",
            "含量描述": "",
            "含量": "4",
            "單位": "g"
        },
        {
            "成分名稱": "炙甘草",
            "含量描述": "",
            "含量": "2",
            "單位": "g"
        },
        {
            "成分名稱": "牡丹皮",
            "含量描述": "",
            "含量": "2.5",
            "單位": "g"
        },
        {
            "成分名稱": "山梔子",
            "含量描述": "",
            "含量": "2.5",
            "單位": "g"
        },
        {
            "成分名稱": "煨薑",
            "含量描述": "",
            "含量": "4",
            "單位": "g"
        },
        {
            "成分名稱": "薄荷",
            "含量描述": "",
            "含量": "2",
            "單位": "g"
        },
        {
            "成分名稱": "",
            "含量描述": "以上生藥製成浸膏8.25g",
            "含量": "",
            "單位": ""
        },
        {
            "成分名稱": "澱粉",
            "含量描述": "",
            "含量": "8.25",
            "單位": "g"
        }
    ]
}