{
    "code": "03001114",
    "url": "https:\/\/service.mohw.gov.tw\/DOCMAP\/CusSite\/TCMLResultDetail.aspx?LICEWORDID=03&LICENUM=001114",
    "中文品名": "”百壽”追風化濕丸",
    "英文品名": "ZHUI FENG HUA SHI WAN \"BAI SHOU\"",
    "許可證字號": "衛署成製字第001114號",
    "發證日期": "1973-09-17",
    "有效日期": "2010-02-28",
    "製造商名稱": "科達製藥股份有限公司",
    "製造商地址": "桃園縣平鎮市湧豐里工業三路20-1號",
    "申請商名稱": "百壽製藥廠有限公司",
    "效能": "",
    "適應症": "驅風袪濕、腰膝痠痛、屈伸不便、筋骨攣痛",
    "劑型": "丸劑",
    "類別": "",
    "包裝": "40-500、600、700、800、900、1000粒→塑膠瓶裝。",
    "單複方": "複方",
    "限制項目": "",
    "ingredients": [
        {
            "成分名稱": "",
            "含量描述": "每丸４５０毫克中含有：",
            "含量": "",
            "單位": ""
        },
        {
            "成分名稱": "獨活",
            "含量描述": "",
            "含量": "25.0000",
            "單位": "mg"
        },
        {
            "成分名稱": "當歸",
            "含量描述": "",
            "含量": "15.0000",
            "單位": "mg"
        },
        {
            "成分名稱": "人參",
            "含量描述": "",
            "含量": "15.0000",
            "單位": "mg"
        },
        {
            "成分名稱": "牛膝",
            "含量描述": "",
            "含量": "20.0000",
            "單位": "mg"
        },
        {
            "成分名稱": "桂枝",
            "含量描述": "",
            "含量": "15.0000",
            "單位": "mg"
        },
        {
            "成分名稱": "熟地黃",
            "含量描述": "",
            "含量": "15.0000",
            "單位": "mg"
        },
        {
            "成分名稱": "杜仲",
            "含量描述": "",
            "含量": "20.0000",
            "單位": "mg"
        },
        {
            "成分名稱": "川芎",
            "含量描述": "",
            "含量": "20.0000",
            "單位": "mg"
        },
        {
            "成分名稱": "秦芄",
            "含量描述": "",
            "含量": "20.0000",
            "單位": "mg"
        },
        {
            "成分名稱": "甘草",
            "含量描述": "",
            "含量": "15.0000",
            "單位": "mg"
        },
        {
            "成分名稱": "防風",
            "含量描述": "",
            "含量": "20.0000",
            "單位": "mg"
        },
        {
            "成分名稱": "白芍藥",
            "含量描述": "",
            "含量": "20.0000",
            "單位": "mg"
        },
        {
            "成分名稱": "茯苓",
            "含量描述": "",
            "含量": "15.0000",
            "單位": "mg"
        },
        {
            "成分名稱": "桑寄生",
            "含量描述": "",
            "含量": "30.0000",
            "單位": "mg"
        },
        {
            "成分名稱": "細辛",
            "含量描述": "",
            "含量": "15.0000",
            "單位": "mg"
        },
        {
            "成分名稱": "黃蠟",
            "含量描述": "",
            "含量": "10.0000",
            "單位": "mg"
        },
        {
            "成分名稱": "蜂蜜",
            "含量描述": "",
            "含量": "160.0000",
            "單位": "mg"
        }
    ]
}