{
    "code": "03005196",
    "url": "https:\/\/service.mohw.gov.tw\/DOCMAP\/CusSite\/TCMLResultDetail.aspx?LICEWORDID=03&LICENUM=005196",
    "中文品名": "“信効”治傷活血散（和傷活血湯加味去穿山甲）",
    "英文品名": "Chu Sung Hwo Shie Powder \"S.S\"",
    "許可證字號": "衛署成製字第005196號",
    "發證日期": "2004-07-01",
    "有效日期": "2025-02-28",
    "製造商名稱": "晉安製藥股份有限公司",
    "製造商地址": "嘉義縣民雄鄉建國路三段二六０巷九號",
    "申請商名稱": "信効生物科技股份有限公司",
    "效能": "",
    "適應症": "跌打損傷、瘀血、紅腫。",
    "劑型": "散劑",
    "類別": "成藥",
    "包裝": "12~500公克塑膠瓶裝",
    "單複方": "複方",
    "限制項目": "",
    "ingredients": [
        {
            "成分名稱": "",
            "含量描述": "每公克中含有:",
            "含量": "",
            "單位": ""
        },
        {
            "成分名稱": "川大黃",
            "含量描述": "",
            "含量": "194",
            "單位": "mg"
        },
        {
            "成分名稱": "桃仁",
            "含量描述": "",
            "含量": "194",
            "單位": "mg"
        },
        {
            "成分名稱": "當歸",
            "含量描述": "",
            "含量": "78",
            "單位": "mg"
        },
        {
            "成分名稱": "威靈仙",
            "含量描述": "",
            "含量": "78",
            "單位": "mg"
        },
        {
            "成分名稱": "紅花",
            "含量描述": "",
            "含量": "78",
            "單位": "mg"
        },
        {
            "成分名稱": "蘇木",
            "含量描述": "",
            "含量": "78",
            "單位": "mg"
        },
        {
            "成分名稱": "生地黃",
            "含量描述": "",
            "含量": "78",
            "單位": "mg"
        },
        {
            "成分名稱": "五加皮",
            "含量描述": "",
            "含量": "78",
            "單位": "mg"
        },
        {
            "成分名稱": "乳香",
            "含量描述": "",
            "含量": "19",
            "單位": "mg"
        },
        {
            "成分名稱": "栝樓根",
            "含量描述": "",
            "含量": "19",
            "單位": "mg"
        },
        {
            "成分名稱": "沒藥",
            "含量描述": "",
            "含量": "19",
            "單位": "mg"
        },
        {
            "成分名稱": "川芎",
            "含量描述": "",
            "含量": "19",
            "單位": "mg"
        },
        {
            "成分名稱": "血竭",
            "含量描述": "",
            "含量": "7",
            "單位": "mg"
        },
        {
            "成分名稱": "甘草",
            "含量描述": "",
            "含量": "12",
            "單位": "mg"
        },
        {
            "成分名稱": "代赭石",
            "含量描述": "",
            "含量": "32",
            "單位": "mg"
        },
        {
            "成分名稱": "薄荷",
            "含量描述": "",
            "含量": "17",
            "單位": "mg"
        }
    ]
}