{
    "code": "03006049",
    "url": "https:\/\/service.mohw.gov.tw\/DOCMAP\/CusSite\/TCMLResultDetail.aspx?LICEWORDID=03&LICENUM=006049",
    "time": "2020-03-05 01:51:47",
    "中文品名": "“南都”治濁固本丸",
    "英文品名": "Chuyr Drow Guh Been Pills“N.T.”",
    "許可證字號": "衛署成製字第006049號",
    "發證日期": "2010-02-06",
    "有效日期": "2025-02-28",
    "製造商名稱": "南都化學製藥股份有限公司＊",
    "製造商地址": "臺南市佳里區佳化里三十九號",
    "申請商名稱": "南都化學製藥股份有限公司＊",
    "效能": "清熱、利溼。",
    "適應症": "溼熱下注、頻尿白濁。",
    "劑型": "丸劑",
    "類別": "成藥",
    "包裝": "36~1000粒塑膠瓶裝",
    "單複方": "複方",
    "限制項目": "",
    "ingredients": [
        {
            "成分名稱": "",
            "含量描述": "每丸(500mg)中含有：",
            "含量": "",
            "單位": ""
        },
        {
            "成分名稱": "蓮鬚",
            "含量描述": "",
            "含量": "46",
            "單位": "mg"
        },
        {
            "成分名稱": "黃連",
            "含量描述": "",
            "含量": "46",
            "單位": "mg"
        },
        {
            "成分名稱": "茯苓",
            "含量描述": "",
            "含量": "23",
            "單位": "mg"
        },
        {
            "成分名稱": "砂仁",
            "含量描述": "",
            "含量": "23",
            "單位": "mg"
        },
        {
            "成分名稱": "益智仁",
            "含量描述": "",
            "含量": "23",
            "單位": "mg"
        },
        {
            "成分名稱": "半夏",
            "含量描述": "",
            "含量": "23",
            "單位": "mg"
        },
        {
            "成分名稱": "黃柏",
            "含量描述": "",
            "含量": "23",
            "單位": "mg"
        },
        {
            "成分名稱": "炙甘草",
            "含量描述": "",
            "含量": "69",
            "單位": "mg"
        },
        {
            "成分名稱": "豬苓",
            "含量描述": "",
            "含量": "57",
            "單位": "mg"
        },
        {
            "成分名稱": "蜂蜜",
            "含量描述": "",
            "含量": "167",
            "單位": "mg"
        }
    ]
}