{
    "code": "03006740",
    "url": "https:\/\/service.mohw.gov.tw\/DOCMAP\/CusSite\/TCMLResultDetail.aspx?LICEWORDID=03&LICENUM=006740",
    "中文品名": "百龍丸（參葺固本丸）",
    "英文品名": "BAE LONG PILLS \"SAN YANG\"",
    "許可證字號": "衛署成製字第006740號",
    "發證日期": "1986-04-16",
    "有效日期": "1993-04-16",
    "製造商名稱": "臺灣三陽製藥廠股份有公司",
    "製造商地址": "屏東縣潮州鎮蓬萊里榮田路三六號",
    "申請商名稱": "臺灣三陽製藥廠股份有限公司",
    "效能": "",
    "適應症": "元氣不足　腰痛耳鳴四肢痠軟形體瘦弱",
    "劑型": "",
    "類別": "成藥",
    "包裝": "24~500、600、1000公克",
    "單複方": "複方",
    "限制項目": "",
    "ingredients": [
        {
            "成分名稱": "",
            "含量描述": "每丸（７　５Ｇ）中含有：",
            "含量": "",
            "單位": ""
        },
        {
            "成分名稱": "人參",
            "含量描述": "",
            "含量": "345.0000",
            "單位": "mg"
        },
        {
            "成分名稱": "鹿茸",
            "含量描述": "",
            "含量": "172.5000",
            "單位": "mg"
        },
        {
            "成分名稱": "白芍",
            "含量描述": "",
            "含量": "172.5000",
            "單位": "mg"
        },
        {
            "成分名稱": "小茴香",
            "含量描述": "",
            "含量": "172.5000",
            "單位": "mg"
        },
        {
            "成分名稱": "陳皮",
            "含量描述": "",
            "含量": "172.5000",
            "單位": "mg"
        },
        {
            "成分名稱": "白朮",
            "含量描述": "",
            "含量": "172.5000",
            "單位": "mg"
        },
        {
            "成分名稱": "黃耆",
            "含量描述": "",
            "含量": "230.0000",
            "單位": "mg"
        },
        {
            "成分名稱": "川牛膝",
            "含量描述": "",
            "含量": "230.0000",
            "單位": "mg"
        },
        {
            "成分名稱": "桂心",
            "含量描述": "",
            "含量": "230.0000",
            "單位": "mg"
        },
        {
            "成分名稱": "枸杞子",
            "含量描述": "",
            "含量": "230.0000",
            "單位": "mg"
        },
        {
            "成分名稱": "巴戟肉",
            "含量描述": "",
            "含量": "345.0000",
            "單位": "mg"
        },
        {
            "成分名稱": "菟絲子",
            "含量描述": "",
            "含量": "345.0000",
            "單位": "mg"
        },
        {
            "成分名稱": "山藥",
            "含量描述": "",
            "含量": "345.0000",
            "單位": "mg"
        },
        {
            "成分名稱": "茯神",
            "含量描述": "",
            "含量": "345.0000",
            "單位": "mg"
        },
        {
            "成分名稱": "肉蓯蓉",
            "含量描述": "",
            "含量": "345.0000",
            "單位": "mg"
        },
        {
            "成分名稱": "當歸",
            "含量描述": "",
            "含量": "345.0000",
            "單位": "mg"
        },
        {
            "成分名稱": "熟地黃",
            "含量描述": "",
            "含量": "690.0000",
            "單位": ""
        },
        {
            "成分名稱": "甘草",
            "含量描述": "",
            "含量": "115.0000",
            "單位": "mg"
        },
        {
            "成分名稱": "蜂蜜",
            "含量描述": "",
            "含量": "2497.5000",
            "單位": "mg"
        }
    ]
}