{
    "code": "03006779",
    "url": "https:\/\/service.mohw.gov.tw\/DOCMAP\/CusSite\/TCMLResultDetail.aspx?LICEWORDID=03&LICENUM=006779",
    "中文品名": "天保達摩運氣散",
    "英文品名": "",
    "許可證字號": "衛署成製字第006779號",
    "發證日期": "1986-05-26",
    "有效日期": "1998-12-10",
    "製造商名稱": "天保製藥股份有限公司",
    "製造商地址": "高雄市鼓山區鼓山一路一六一巷六一號",
    "申請商名稱": "天保製藥股份有限公司",
    "效能": "",
    "適應症": "食積消化不良、胃酸過多、食慾不振、泄傷腹。",
    "劑型": "",
    "類別": "成藥",
    "包裝": "36~500、600、760、",
    "單複方": "複方",
    "限制項目": "",
    "ingredients": [
        {
            "成分名稱": "",
            "含量描述": "每１公克中含有：",
            "含量": "",
            "單位": ""
        },
        {
            "成分名稱": "木香",
            "含量描述": "",
            "含量": "100.0000",
            "單位": "mg"
        },
        {
            "成分名稱": "冰片",
            "含量描述": "",
            "含量": "47.0000",
            "單位": "mg"
        },
        {
            "成分名稱": "砂仁",
            "含量描述": "",
            "含量": "93.0000",
            "單位": "mg"
        },
        {
            "成分名稱": "沈香",
            "含量描述": "",
            "含量": "47.0000",
            "單位": "mg"
        },
        {
            "成分名稱": "桔梗",
            "含量描述": "",
            "含量": "186.0000",
            "單位": "mg"
        },
        {
            "成分名稱": "厚朴",
            "含量描述": "",
            "含量": "100.0000",
            "單位": "mg"
        },
        {
            "成分名稱": "代赭石",
            "含量描述": "",
            "含量": "5.0000",
            "單位": "mg"
        },
        {
            "成分名稱": "大黃",
            "含量描述": "",
            "含量": "47.0000",
            "單位": "mg"
        },
        {
            "成分名稱": "藿香",
            "含量描述": "",
            "含量": "47.0000",
            "單位": "mg"
        },
        {
            "成分名稱": "薄荷",
            "含量描述": "",
            "含量": "47.0000",
            "單位": "mg"
        },
        {
            "成分名稱": "丁香",
            "含量描述": "",
            "含量": "47.0000",
            "單位": "mg"
        },
        {
            "成分名稱": "黃連",
            "含量描述": "",
            "含量": "47.0000",
            "單位": "mg"
        },
        {
            "成分名稱": "蒼朮",
            "含量描述": "",
            "含量": "47.0000",
            "單位": "mg"
        },
        {
            "成分名稱": "肉桂",
            "含量描述": "",
            "含量": "47.0000",
            "單位": "mg"
        },
        {
            "成分名稱": "白朮",
            "含量描述": "",
            "含量": "93.0000",
            "單位": "mg"
        }
    ]
}