{
    "code": "03008596",
    "url": "https:\/\/service.mohw.gov.tw\/DOCMAP\/CusSite\/TCMLResultDetail.aspx?LICEWORDID=03&LICENUM=008596",
    "中文品名": "“南美”爽肌噴劑（回陽玉龍膏加減味）",
    "英文品名": "",
    "許可證字號": "衛署成製字第008596號",
    "發證日期": "2019-11-02",
    "有效日期": "2025-02-28",
    "製造商名稱": "南美製藥股份有限公司",
    "製造商地址": "高雄市大寮區大有二街8號",
    "申請商名稱": null,
    "效能": "",
    "適應症": "跌打損傷、筋肉疼痛、行瘀活血、消腫止癢。",
    "劑型": "外用液劑",
    "類別": "成藥",
    "包裝": "1000毫升以下塑膠瓶裝",
    "單複方": "複方",
    "限制項目": "",
    "ingredients": [
        {
            "成分名稱": "",
            "含量描述": "每毫升中含有： ",
            "含量": "",
            "單位": ""
        },
        {
            "成分名稱": "草烏頭",
            "含量描述": "",
            "含量": "2.4",
            "單位": "mg"
        },
        {
            "成分名稱": "天南星",
            "含量描述": "",
            "含量": "0.8",
            "單位": "mg"
        },
        {
            "成分名稱": "乾薑",
            "含量描述": "",
            "含量": "1.6",
            "單位": "mg"
        },
        {
            "成分名稱": "白芷",
            "含量描述": "",
            "含量": "0.8",
            "單位": "mg"
        },
        {
            "成分名稱": "赤芍",
            "含量描述": "",
            "含量": "0.8",
            "單位": "mg"
        },
        {
            "成分名稱": "肉桂",
            "含量描述": "",
            "含量": "0.4",
            "單位": "mg"
        },
        {
            "成分名稱": "川七",
            "含量描述": "",
            "含量": "1.6",
            "單位": "mg"
        },
        {
            "成分名稱": "金不換",
            "含量描述": "",
            "含量": "1.6",
            "單位": "mg"
        },
        {
            "成分名稱": "薄荷腦",
            "含量描述": "",
            "含量": "78.1",
            "單位": "mg"
        },
        {
            "成分名稱": "冬綠油",
            "含量描述": "",
            "含量": "30.2",
            "單位": "mg"
        },
        {
            "成分名稱": "",
            "含量描述": "酒精加至1ml",
            "含量": "",
            "單位": ""
        }
    ]
}