{
    "code": "03008988",
    "url": "https:\/\/service.mohw.gov.tw\/DOCMAP\/CusSite\/TCMLResultDetail.aspx?LICEWORDID=03&LICENUM=008988",
    "中文品名": "鬱喀適運功散",
    "英文品名": "",
    "許可證字號": "衛署成製字第008988號",
    "發證日期": "1991-11-28",
    "有效日期": "2006-10-17",
    "製造商名稱": "港香蘭藥廠股份有限公司",
    "製造商地址": "台南市永康區永康工業區環工路九號",
    "申請商名稱": "港香蘭藥廠股份有限公司",
    "效能": "",
    "適應症": "打撲損傷引起之胸部疼痛　袪傷解鬱",
    "劑型": "",
    "類別": "成藥",
    "包裝": "24~500、600、1000公克  36~500、600、760、",
    "單複方": "複方",
    "限制項目": "",
    "ingredients": [
        {
            "成分名稱": "",
            "含量描述": "每公克中含有：",
            "含量": "",
            "單位": ""
        },
        {
            "成分名稱": "三七",
            "含量描述": "",
            "含量": "0.0800",
            "單位": "ml"
        },
        {
            "成分名稱": "沒藥",
            "含量描述": "",
            "含量": "0.0400",
            "單位": "ml"
        },
        {
            "成分名稱": "代赭石",
            "含量描述": "",
            "含量": "0.0800",
            "單位": "ml"
        },
        {
            "成分名稱": "孔香",
            "含量描述": "",
            "含量": "0.0400",
            "單位": "ml"
        },
        {
            "成分名稱": "紅花",
            "含量描述": "",
            "含量": "0.0800",
            "單位": "ml"
        },
        {
            "成分名稱": "甘草",
            "含量描述": "",
            "含量": "0.0900",
            "單位": "ml"
        },
        {
            "成分名稱": "丁香",
            "含量描述": "",
            "含量": "0.0400",
            "單位": "ml"
        },
        {
            "成分名稱": "蘇木",
            "含量描述": "",
            "含量": "0.0800",
            "單位": "ml"
        },
        {
            "成分名稱": "貝母",
            "含量描述": "",
            "含量": "0.0800",
            "單位": "ml"
        },
        {
            "成分名稱": "木香",
            "含量描述": "",
            "含量": "0.0400",
            "單位": "ml"
        },
        {
            "成分名稱": "香附",
            "含量描述": "",
            "含量": "0.0800",
            "單位": "ml"
        },
        {
            "成分名稱": "桔梗",
            "含量描述": "",
            "含量": "0.0800",
            "單位": "ml"
        },
        {
            "成分名稱": "澤蘭",
            "含量描述": "",
            "含量": "0.0800",
            "單位": "ml"
        },
        {
            "成分名稱": "骨碎補",
            "含量描述": "",
            "含量": "0.0800",
            "單位": "ml"
        },
        {
            "成分名稱": "薄荷腦",
            "含量描述": "",
            "含量": "0.0100",
            "單位": "ml"
        },
        {
            "成分名稱": "梅片",
            "含量描述": "",
            "含量": "0.0200",
            "單位": "ml"
        }
    ]
}