{
    "code": "03013773",
    "url": "https:\/\/service.mohw.gov.tw\/DOCMAP\/CusSite\/TCMLResultDetail.aspx?LICEWORDID=03&LICENUM=013773",
    "中文品名": "“愛康”愛你好護理寶丸（烏雞丸減味）",
    "英文品名": "",
    "許可證字號": "衛署成製字第013773號",
    "發證日期": "2025-07-15",
    "有效日期": "2030-09-30",
    "製造商名稱": "愛康製藥廠股份有限公司",
    "製造商地址": "彰化縣田中鎮新工一路１６號",
    "申請商名稱": "愛康製藥廠股份有限公司",
    "效能": "",
    "適應症": "脾胃虛弱、血氣不足、經侯不調。",
    "劑型": "丸劑",
    "類別": "成藥",
    "包裝": "36~1000粒塑膠瓶裝",
    "單複方": "複方",
    "限制項目": "內衛換證（不得作為處方依據）",
    "ingredients": [
        {
            "成分名稱": "",
            "含量描述": "每丸(500mg)中含有：",
            "含量": "",
            "單位": ""
        },
        {
            "成分名稱": "杜仲",
            "含量描述": "",
            "含量": "40.0",
            "單位": "mg"
        },
        {
            "成分名稱": "人參",
            "含量描述": "",
            "含量": "20.0",
            "單位": "mg"
        },
        {
            "成分名稱": "砂仁",
            "含量描述": "",
            "含量": "20.0",
            "單位": "mg"
        },
        {
            "成分名稱": "川芎",
            "含量描述": "",
            "含量": "40.0",
            "單位": "mg"
        },
        {
            "成分名稱": "甘草",
            "含量描述": "",
            "含量": "20.0",
            "單位": "mg"
        },
        {
            "成分名稱": "香附",
            "含量描述": "",
            "含量": "80.0",
            "單位": "mg"
        },
        {
            "成分名稱": "白朮",
            "含量描述": "",
            "含量": "40.0",
            "單位": "mg"
        },
        {
            "成分名稱": "肉蓯蓉",
            "含量描述": "",
            "含量": "20.0",
            "單位": "mg"
        },
        {
            "成分名稱": "當歸",
            "含量描述": "",
            "含量": "40.0",
            "單位": "mg"
        },
        {
            "成分名稱": "補骨脂",
            "含量描述": "",
            "含量": "30.0",
            "單位": "mg"
        },
        {
            "成分名稱": "茯苓",
            "含量描述": "",
            "含量": "40.0",
            "單位": "mg"
        },
        {
            "成分名稱": "小茴香",
            "含量描述": "",
            "含量": "30.0",
            "單位": "mg"
        },
        {
            "成分名稱": "蜂蜜",
            "含量描述": "",
            "含量": "80.0",
            "單位": "mg"
        }
    ]
}