{
    "code": "03014023",
    "url": "https:\/\/service.mohw.gov.tw\/DOCMAP\/CusSite\/TCMLResultDetail.aspx?LICEWORDID=03&LICENUM=014023",
    "中文品名": "爽聲保丸（鐵笛丸）",
    "英文品名": "Shuang Sheng Bao Pill",
    "許可證字號": "衛署成製字第014023號",
    "發證日期": "2006-01-25",
    "有效日期": "2031-01-25",
    "製造商名稱": "宏星製藥廠股份有限公司",
    "製造商地址": "桃園市中壢區南園路1之1號",
    "申請商名稱": "生都藥品有限公司",
    "效能": "",
    "適應症": "喉痛聲啞、口燥咽乾",
    "劑型": "丸劑",
    "類別": "成藥",
    "包裝": "6~1000粒塑膠瓶及15粒鋁箔片x1~66片盒裝",
    "單複方": "複方",
    "限制項目": "",
    "ingredients": [
        {
            "成分名稱": "",
            "含量描述": "每丸(1g)中含有：",
            "含量": "",
            "單位": ""
        },
        {
            "成分名稱": "薄荷",
            "含量描述": "",
            "含量": "150",
            "單位": "mg"
        },
        {
            "成分名稱": "甘草",
            "含量描述": "",
            "含量": "73",
            "單位": "mg"
        },
        {
            "成分名稱": "桔梗",
            "含量描述": "",
            "含量": "73",
            "單位": "mg"
        },
        {
            "成分名稱": "百藥煎",
            "含量描述": "",
            "含量": "73",
            "單位": "mg"
        },
        {
            "成分名稱": "川芎",
            "含量描述": "",
            "含量": "93",
            "單位": "mg"
        },
        {
            "成分名稱": "連翹",
            "含量描述": "",
            "含量": "93",
            "單位": "mg"
        },
        {
            "成分名稱": "訶子",
            "含量描述": "",
            "含量": "37",
            "單位": "mg"
        },
        {
            "成分名稱": "砂仁",
            "含量描述": "",
            "含量": "37",
            "單位": "mg"
        },
        {
            "成分名稱": "大黃",
            "含量描述": "",
            "含量": "37",
            "單位": "mg"
        },
        {
            "成分名稱": "蜂蜜",
            "含量描述": "",
            "含量": "334",
            "單位": "mg"
        }
    ]
}