{
    "code": "03014346",
    "url": "https:\/\/service.mohw.gov.tw\/DOCMAP\/CusSite\/TCMLResultDetail.aspx?LICEWORDID=03&LICENUM=014346",
    "time": "2020-03-05 01:51:47",
    "中文品名": "〝立安〞上中下通用痛風丸",
    "英文品名": "Shang Zhong Xia Tong Yong Tong Feng Pill〝L.A.〞",
    "許可證字號": "衛署成製字第014346號",
    "發證日期": "2006-12-20",
    "有效日期": "2021-12-20",
    "製造商名稱": "立安生物科技製藥股份有限公司",
    "製造商地址": "台南市官田區二鎮村工業路3號",
    "申請商名稱": "立安生物科技製藥股份有限公司",
    "效能": "疏風祛痰、清熱燥溼、活血止痛。",
    "適應症": "感受風寒濕邪、挾痰熱、血脈不暢、骨節疼痛。",
    "劑型": "丸劑",
    "類別": "成藥",
    "包裝": "48~1000粒塑膠瓶裝",
    "單複方": "複方",
    "限制項目": "",
    "ingredients": [
        {
            "成分名稱": "",
            "含量描述": "每丸(500mg)中含有：",
            "含量": "",
            "單位": ""
        },
        {
            "成分名稱": "天南星",
            "含量描述": "",
            "含量": "48",
            "單位": "mg"
        },
        {
            "成分名稱": "蒼朮",
            "含量描述": "",
            "含量": "48",
            "單位": "mg"
        },
        {
            "成分名稱": "黃柏",
            "含量描述": "",
            "含量": "48",
            "單位": "mg"
        },
        {
            "成分名稱": "川芎",
            "含量描述": "",
            "含量": "24",
            "單位": "mg"
        },
        {
            "成分名稱": "白芷",
            "含量描述": "",
            "含量": "24",
            "單位": "mg"
        },
        {
            "成分名稱": "神麴",
            "含量描述": "",
            "含量": "24",
            "單位": "mg"
        },
        {
            "成分名稱": "桃仁",
            "含量描述": "",
            "含量": "24",
            "單位": "mg"
        },
        {
            "成分名稱": "威靈仙",
            "含量描述": "",
            "含量": "12",
            "單位": "mg"
        },
        {
            "成分名稱": "羌活",
            "含量描述": "",
            "含量": "12",
            "單位": "mg"
        },
        {
            "成分名稱": "防己",
            "含量描述": "",
            "含量": "24",
            "單位": "mg"
        },
        {
            "成分名稱": "桂枝",
            "含量描述": "",
            "含量": "12",
            "單位": "mg"
        },
        {
            "成分名稱": "紅花",
            "含量描述": "",
            "含量": "6",
            "單位": "mg"
        },
        {
            "成分名稱": "龍膽",
            "含量描述": "",
            "含量": "24",
            "單位": "mg"
        },
        {
            "成分名稱": "蜂蜜",
            "含量描述": "",
            "含量": "170",
            "單位": "mg"
        }
    ]
}