{
    "code": "03014744",
    "url": "https:\/\/service.mohw.gov.tw\/DOCMAP\/CusSite\/TCMLResultDetail.aspx?LICEWORDID=03&LICENUM=014744",
    "中文品名": "〝輝陽〞黃金膏（瑩珠膏加減味）",
    "英文品名": "Hwang Jin Gau〝H.Y〞（Yng Ju Gau Jia Jean Wey）",
    "許可證字號": "衛署成製字第014744號",
    "發證日期": "2007-10-01",
    "有效日期": "2027-10-01",
    "製造商名稱": "輝陽藥品股份有限公司",
    "製造商地址": "屏東縣九如鄉清聖街46巷51號",
    "申請商名稱": "輝陽藥品股份有限公司",
    "效能": "",
    "適應症": "燙傷、蚊蟲咬傷、止癢、消腫、止痛。",
    "劑型": "油膏劑",
    "類別": "成藥",
    "包裝": "1000公克以下塑膠瓶裝",
    "單複方": "複方",
    "限制項目": "",
    "ingredients": [
        {
            "成分名稱": "",
            "含量描述": "每公克中含有：",
            "含量": "",
            "單位": ""
        },
        {
            "成分名稱": "樟腦",
            "含量描述": "",
            "含量": "93",
            "單位": "mg"
        },
        {
            "成分名稱": "冰片",
            "含量描述": "",
            "含量": "6",
            "單位": "mg"
        },
        {
            "成分名稱": "黃柏",
            "含量描述": "",
            "含量": "62",
            "單位": "mg"
        },
        {
            "成分名稱": "薄荷腦",
            "含量描述": "",
            "含量": "10",
            "單位": "mg"
        },
        {
            "成分名稱": "冬綠油",
            "含量描述": "",
            "含量": "5",
            "單位": "mg"
        },
        {
            "成分名稱": "白臘",
            "含量描述": "",
            "含量": "195",
            "單位": "mg"
        },
        {
            "成分名稱": "",
            "含量描述": "食用黃色4號",
            "含量": "",
            "單位": ""
        },
        {
            "成分名稱": "",
            "含量描述": "凡士林加至1g",
            "含量": "",
            "單位": ""
        }
    ]
}