{
    "code": "03014769",
    "url": "https:\/\/service.mohw.gov.tw\/DOCMAP\/CusSite\/TCMLResultDetail.aspx?LICEWORDID=03&LICENUM=014769",
    "中文品名": "“黑矸標”珠碧驚風散",
    "英文品名": "",
    "許可證字號": "衛署成製字第014769號",
    "發證日期": "2007-10-23",
    "有效日期": "2025-02-28",
    "製造商名稱": "昕泰生技製藥股份有限公司",
    "製造商地址": "桃園市大溪區仁善里八鄰仁德北街四五號",
    "申請商名稱": "新永豐藥行",
    "效能": "",
    "適應症": "小兒驚悸夜啼、煩躁不寧、風痰上雍、吐乳青便、鎮驚退熱、疏風順氣。",
    "劑型": "散劑",
    "類別": "成藥",
    "包裝": "1.8~1000公克塑膠瓶裝",
    "單複方": "複方",
    "限制項目": "",
    "ingredients": [
        {
            "成分名稱": "",
            "含量描述": "每公克中含有：",
            "含量": "",
            "單位": ""
        },
        {
            "成分名稱": "膽南星",
            "含量描述": "",
            "含量": "280.84",
            "單位": "mg"
        },
        {
            "成分名稱": "天竺黃",
            "含量描述": "",
            "含量": "213.64",
            "單位": "mg"
        },
        {
            "成分名稱": "川貝母",
            "含量描述": "",
            "含量": "170.51",
            "單位": "mg"
        },
        {
            "成分名稱": "製半夏",
            "含量描述": "",
            "含量": "71.21",
            "單位": "mg"
        },
        {
            "成分名稱": "天麻",
            "含量描述": "",
            "含量": "71.21",
            "單位": "mg"
        },
        {
            "成分名稱": "防風",
            "含量描述": "",
            "含量": "42.13",
            "單位": "mg"
        },
        {
            "成分名稱": "製白附子",
            "含量描述": "",
            "含量": "42.13",
            "單位": "mg"
        },
        {
            "成分名稱": "羌活",
            "含量描述": "",
            "含量": "42.13",
            "單位": "mg"
        },
        {
            "成分名稱": "蟬蛻",
            "含量描述": "",
            "含量": "42.13",
            "單位": "mg"
        },
        {
            "成分名稱": "牛黃",
            "含量描述": "",
            "含量": "14.04",
            "單位": "mg"
        },
        {
            "成分名稱": "冰片",
            "含量描述": "",
            "含量": "7.02",
            "單位": "mg"
        },
        {
            "成分名稱": "胭脂素",
            "含量描述": "",
            "含量": "3.01",
            "單位": "mg"
        }
    ]
}