{
    "code": "03017077",
    "url": "https:\/\/service.mohw.gov.tw\/DOCMAP\/CusSite\/TCMLResultDetail.aspx?LICEWORDID=03&LICENUM=017077",
    "中文品名": "月之康四物飲",
    "英文品名": "Yen Eve's with Cordyceps Sinensis Mycelia Liquid",
    "許可證字號": "衛部成製字第017077號",
    "發證日期": "2021-01-28",
    "有效日期": "2026-01-28",
    "製造商名稱": "台灣漢藥生技股份有限公司",
    "製造商地址": "臺南市佳里區嘉福里115之1號",
    "申請商名稱": "台灣漢藥生技股份有限公司",
    "效能": "",
    "適應症": "",
    "劑型": "內服液劑",
    "類別": "成藥",
    "包裝": "50~1000毫升玻璃瓶及鋁箔袋盒裝",
    "單複方": "複方",
    "限制項目": "外銷專用\n不得為處方依據",
    "ingredients": [
        {
            "成分名稱": "",
            "含量描述": "每毫升中含有： ",
            "含量": "",
            "單位": ""
        },
        {
            "成分名稱": "熟地黃",
            "含量描述": "",
            "含量": "0.0200",
            "單位": "g"
        },
        {
            "成分名稱": "白芍",
            "含量描述": "",
            "含量": "0.0200",
            "單位": "g"
        },
        {
            "成分名稱": "當歸",
            "含量描述": "",
            "含量": "0.0200",
            "單位": "g"
        },
        {
            "成分名稱": "川芎",
            "含量描述": "",
            "含量": "0.0200",
            "單位": "g"
        },
        {
            "成分名稱": "西洋參",
            "含量描述": "",
            "含量": "0.0080",
            "單位": "g"
        },
        {
            "成分名稱": "白朮",
            "含量描述": "",
            "含量": "0.0200",
            "單位": "g"
        },
        {
            "成分名稱": "茯苓",
            "含量描述": "",
            "含量": "0.0200",
            "單位": "g"
        },
        {
            "成分名稱": "炙甘草",
            "含量描述": "",
            "含量": "0.0100",
            "單位": "g"
        },
        {
            "成分名稱": "五味子",
            "含量描述": "",
            "含量": "0.0080",
            "單位": "g"
        },
        {
            "成分名稱": "丹參",
            "含量描述": "",
            "含量": "0.0040",
            "單位": "g"
        },
        {
            "成分名稱": "白芷",
            "含量描述": "",
            "含量": "0.0040",
            "單位": "g"
        },
        {
            "成分名稱": "黃精",
            "含量描述": "",
            "含量": "0.0040",
            "單位": "g"
        },
        {
            "成分名稱": "玉竹",
            "含量描述": "",
            "含量": "0.0040",
            "單位": "g"
        },
        {
            "成分名稱": "紅棗",
            "含量描述": "",
            "含量": "0.0100",
            "單位": "g"
        },
        {
            "成分名稱": "冰糖",
            "含量描述": "",
            "含量": "0.0800",
            "單位": "g"
        },
        {
            "成分名稱": "玫瑰花瓣萃取液",
            "含量描述": "",
            "含量": "0.0010",
            "單位": "g"
        },
        {
            "成分名稱": "石榴汁",
            "含量描述": "",
            "含量": "0.0200",
            "單位": "g"
        },
        {
            "成分名稱": "冬蟲夏草菌絲體",
            "含量描述": "",
            "含量": "0.0014",
            "單位": "g"
        },
        {
            "成分名稱": "",
            "含量描述": "純水加至1ml",
            "含量": "",
            "單位": ""
        }
    ]
}